{"http://bit.ly/mUamoG": "http://www.heise.de/newsticker/meldung/Videoueberwachung-in-Hannover-ist-gesetzwidrig-1280127.html", "http://t.co/7KOCKWBo": "http://hickerspace.org/wiki/Verkehrsampel", "https://t.co/EK4i47UqXY": "https://hickerspace.org/wiki/Workshops#Mini-Workshops", "http://t.co/570DqJTI": "http://hickerspace.org/wiki/Matelade", "http://t.co/Ervcfpwe": "http://twitpic.com/bwg1hi", "http://hickerspace.org/wiki/Kontakt": "http://hickerspace.org/wiki/Kontakt", "http://t.co/gCDnHxTe": "http://twitpic.com/bwd90y", "http://t.co/Baqp3447": "http://bit.ly/vyvzyN", "http://t.co/ao7A0yNq": "http://twitpic.com/blyi13", "http://tiny.cc/soldercomic": "http://mightyohm.com/blog/2011/04/soldering-is-easy-comic-book/", "http://is.gd/AmySHx": "http://hickerspace.org/wiki/User_Tracking"}